dmsclient/__init__.py
dmsclient/cli.py
dmsclient/core/__init__.py
dmsclient/core/client.py
dmsclient/core/config.py
dmsclient/core/models.py
dmsclient/core/utility.py
dmsclient-1.5.2.dist-info/LICENSE.txt
dmsclient-1.5.2.dist-info/METADATA
dmsclient-1.5.2.dist-info/WHEEL
dmsclient-1.5.2.dist-info/entry_points.txt
dmsclient-1.5.2.dist-info/top_level.txt
dmsclient-1.5.2.dist-info/RECORD
