Metadata-Version: 2.1
Name: dmsclient
Version: 1.5.2
Summary: Library and command line interface to interact with Drink Management System of Fachschaft TF Uni Freiburg.
Home-page: UNKNOWN
Author: David-Elias Künstle
Author-email: dmsclient@kuenstle.me
License: MIT
Platform: UNKNOWN
Requires-Dist: aiohttp (>=3.1.1)
Requires-Dist: docopt (>=0.6.0)
Requires-Dist: requests (>=2.18.0)
Requires-Dist: tabulate (>=0.7.0)
Requires-Dist: infi.docopt-completion (>=0.2.8)
